weatherloc/__init__.py
weatherloc/weatherloc.py
weatherloc/commands/__init__.py
weatherloc/commands/astronomy.py
weatherloc/commands/current.py
weatherloc/commands/forecast.py
weatherloc/commands/ip_lookup.py
weatherloc/commands/search.py
weatherloc/commands/sports.py
weatherloc/commands/errors/__init__.py
weatherloc/commands/errors/exceptions.py
weatherloc/commands/models/__init__.py
weatherloc/commands/models/aqi.py
weatherloc/commands/models/astro.py
weatherloc/commands/models/condition.py
weatherloc/commands/models/day.py
weatherloc/commands/models/hour.py
weatherloc/commands/models/location.py
WeatherLoc-1.0.1.dist-info/LICENSE
WeatherLoc-1.0.1.dist-info/METADATA
WeatherLoc-1.0.1.dist-info/WHEEL
WeatherLoc-1.0.1.dist-info/top_level.txt
WeatherLoc-1.0.1.dist-info/RECORD
