Metadata-Version: 2.1
Name: WeatherLoc
Version: 1.0.1
Summary: Weather and geolocation API
Home-page: https://github.com/Ghoul072/pyweather
Author: Yaseen
Author-email: <ahm3d.yaseen@gmail.com>
Keywords: weatherloc,python,weather,geolocation,meteorology,api,weatherapi,pyweather,python-weather,science,pyweather,ip,ip-finder,location
Classifier: Development Status :: 2 - Pre-Alpha
Classifier: Intended Audience :: Developers
Classifier: Intended Audience :: Education
Classifier: Intended Audience :: Science/Research
Classifier: Topic :: Scientific/Engineering :: Atmospheric Science
Classifier: Programming Language :: Python :: 3
Classifier: License :: OSI Approved :: MIT License
Classifier: Operating System :: OS Independent
License-File: LICENSE
Requires-Dist: requests (==2.28.2)
Requires-Dist: charset-normalizer
Requires-Dist: urllib3
Requires-Dist: idna
Requires-Dist: certifi
